uhttp.py
uhttp-2.0.0.dist-info/LICENSE
uhttp-2.0.0.dist-info/METADATA
uhttp-2.0.0.dist-info/WHEEL
uhttp-2.0.0.dist-info/RECORD
