Metadata-Version: 2.1
Name: uhttp
Version: 2.0.0
Summary: Pythonic Web Development
Home-page: https://github.com/0x67757300/uHTTP
License: MIT
Keywords: asgi,web,http
Author: gus
Author-email: 0x67757300@gmail.com
Requires-Python: >=3.9,<4.0
Classifier: License :: OSI Approved :: MIT License
Classifier: Programming Language :: Python :: 3
Classifier: Programming Language :: Python :: 3.9
Classifier: Programming Language :: Python :: 3.10
Classifier: Programming Language :: Python :: 3.11
Classifier: Programming Language :: Python :: 3.12
Project-URL: Repository, https://github.com/0x67757300/uHTTP
